MANIFEST.in
setup.py
django_noaa/__init__.py
django_noaa/admin.py
django_noaa/constants.py
django_noaa/models.py
django_noaa/settings.py
django_noaa.egg-info/PKG-INFO
django_noaa.egg-info/SOURCES.txt
django_noaa.egg-info/dependency_links.txt
django_noaa.egg-info/not-zip-safe
django_noaa.egg-info/requires.txt
django_noaa.egg-info/top_level.txt
django_noaa/management/__init__.py
django_noaa/management/commands/__init__.py
django_noaa/management/commands/import_noaa_stations.py
django_noaa/management/commands/import_noaa_temperatures.py
django_noaa/migrations/0001_initial.py
django_noaa/migrations/0002_auto__chg_field_station_elevation__chg_field_station_wban.py
django_noaa/migrations/0003_auto__add_field_station_load_temperatures_min_year__add_field_station_.py
django_noaa/migrations/0004_auto__add_temperature__add_unique_temperature_station_obs_start_dateti.py
django_noaa/migrations/__init__.py
django_noaa/reference/USCRN_HOURLY0203.csv