Metadata-Version: 1.1
Name: django-noaa
Version: 0.1.1
Summary: Django app for downloading and storing historical weather data from NOAA.
Home-page: https://github.com/chrisspen/django-noaa
Author: Chris Spencer
Author-email: chrisspen@gmail.com
License: LGPL
Platform: UNKNOWN
Classifier: Environment :: Web Environment
Classifier: Intended Audience :: Developers
Classifier: License :: OSI Approved :: GNU Lesser General Public License v3 (LGPLv3)
Classifier: Operating System :: OS Independent
Classifier: Programming Language :: Python
Classifier: Framework :: Django
Classifier: Development Status :: 4 - Beta
